__init__.py
wpcaller.py
webull_pay_caller_mcp-0.1.3.dist-info/METADATA
webull_pay_caller_mcp-0.1.3.dist-info/WHEEL
webull_pay_caller_mcp-0.1.3.dist-info/entry_points.txt
webull_pay_caller_mcp-0.1.3.dist-info/top_level.txt
webull_pay_caller_mcp-0.1.3.dist-info/RECORD
