Metadata-Version: 2.4
Name: webull-pay-caller-mcp
Version: 0.1.3
Summary: 通过 Webull Pay OpenAPI 下单 / 查行情 / 账户余额
Requires-Python: >=3.10
Requires-Dist: httpx>=0.28.1
Requires-Dist: mcp[cli]>=1.6.0
Requires-Dist: webullpay-python-sdk-core>=0.1.0
Requires-Dist: webullpay-python-sdk-mdata>=0.1.0
Requires-Dist: webullpay-python-sdk-quotes-core>=0.1.0
Requires-Dist: webullpay-python-sdk-trade>=0.1.0
Requires-Dist: webullpay-python-sdk-trade-events-core>=0.1.0
Requires-Dist: six>=1.16.0
Requires-Dist: PySocks>=1.7.1
